LICENSE
MANIFEST.in
README.rst
setup.cfg
setup.py
django_voice_bot.egg-info/PKG-INFO
django_voice_bot.egg-info/SOURCES.txt
django_voice_bot.egg-info/dependency_links.txt
django_voice_bot.egg-info/requires.txt
django_voice_bot.egg-info/top_level.txt
voice_bot/__init__.py
voice_bot/admin.py
voice_bot/decorators.py
voice_bot/models.py
voice_bot/urls.py
voice_bot/views.py
voice_bot/migrations/0001_initial.py
voice_bot/migrations/0002_auto_20201129_0145.py
voice_bot/migrations/0003_bot_speech_full.py
voice_bot/migrations/0004_auto_20201129_0528.py
voice_bot/migrations/0005_auto_20201129_0635.py
voice_bot/migrations/0006_auto_20201129_0657.py
voice_bot/migrations/0007_bot_repeat_commands.py
voice_bot/migrations/__init__.py
voice_bot/templates/bot_include.html
voice_bot/templates/chat_script.html